<?xml version="1.0" encoding="gb2312" standalone="yes" ?>
<Stage>
    <Object Guid="C85B44AF493E460F9D31D96A3BF0FC2E" Desc="大副吉伯特" config="npc_zlm001_0047" Layer="" MaxRefreshCount="" x="-3762.396484" y="17.400259" z="7518.841309" IsY="0" Radius="0.1" UseSuicideTime="" PeaceAction="" PathID="" amount="1" RefreshMode="" RefreshPointSet="" RefreshTime="1" sx="" sy="" sz="" fOrg="0.3" PatrolMode="" RoadSignID="">
        <Task Issue="" Refer="" />
        <OrganData IsOrgan="" Controllers="" IniState="" AutoResume="" ResumeState="" ResumeInterval="" SpringMode="" ResponseMode="" />
    </Object>
    <Object Guid="D928C9AD0F3848759A86E4CF5A83FC79" Desc="水手乔伊斯" config="npc_zlm001_0045" Layer="" MaxRefreshCount="" x="-3765.456055" y="17.400259" z="7519.784668" IsY="0" Radius="0.1" UseSuicideTime="" PeaceAction="" PathID="" amount="1" RefreshMode="" RefreshPointSet="" RefreshTime="1" sx="" sy="" sz="" fOrg="0.045" PatrolMode="" RoadSignID="">
        <Task Issue="" Refer="" />
        <OrganData IsOrgan="" Controllers="" IniState="" AutoResume="" ResumeState="" ResumeInterval="" SpringMode="" ResponseMode="" />
    </Object>
    <Object Guid="BE4DF16708A04A15B9C772C6C0CF00C4" Desc="源机构长老菲利克斯" config="npc_zlm001_0048" Layer="" MaxRefreshCount="" x="-3749.629883" y="17.830259" z="7547.762207" IsY="0" Radius="0.1" UseSuicideTime="" PeaceAction="" PathID="" amount="1" RefreshMode="" RefreshPointSet="" RefreshTime="1" sx="" sy="" sz="" fOrg="1.685" PatrolMode="" RoadSignID="">
        <Task Issue="" Refer="" />
        <OrganData IsOrgan="" Controllers="" IniState="" AutoResume="" ResumeState="" ResumeInterval="" SpringMode="" ResponseMode="" />
    </Object>
    <Object Guid="B3A314C193D0476F98EF2D0DE1CF0C04" Desc="军需官佛罗伦丝" config="npc_zlm001_0046" Layer="" MaxRefreshCount="" x="-3697.543701" y="15.490196" z="7484.941895" IsY="0" Radius="0.1" UseSuicideTime="" PeaceAction="" PathID="" amount="1" RefreshMode="" RefreshPointSet="" RefreshTime="1" sx="" sy="" sz="" fOrg="0" PatrolMode="" RoadSignID="">
        <Task Issue="" Refer="" />
        <OrganData IsOrgan="" Controllers="" IniState="" AutoResume="" ResumeState="" ResumeInterval="" SpringMode="" ResponseMode="" />
    </Object>
    <Object Guid="83785EF18BA043FFA2EA208E1BE4F654" Desc="研究员格洛佛" config="npc_zlm001_0049" Layer="" MaxRefreshCount="" x="-3683.049072" y="15.490197" z="7501.59375" IsY="0" Radius="0.1" UseSuicideTime="" PeaceAction="" PathID="" amount="1" RefreshMode="" RefreshPointSet="" RefreshTime="1" sx="" sy="" sz="" fOrg="3.458184" PatrolMode="" RoadSignID="">
        <Task Issue="" Refer="" />
        <OrganData IsOrgan="" Controllers="" IniState="" AutoResume="" ResumeState="" ResumeInterval="" SpringMode="" ResponseMode="" />
    </Object>
    <Object Guid="226D7AB564664054B270C9F90A03C12C" Desc="研究员杰勒米" config="npc_zlm001_0050" Layer="" MaxRefreshCount="" x="-3651.280273" y="16.381786" z="7467.444824" IsY="0" Radius="0.1" UseSuicideTime="" PeaceAction="" PathID="" amount="1" RefreshMode="" RefreshPointSet="" RefreshTime="1" sx="" sy="" sz="" fOrg="3.395002" PatrolMode="" RoadSignID="">
        <Task Issue="" Refer="" />
        <OrganData IsOrgan="" Controllers="" IniState="" AutoResume="" ResumeState="" ResumeInterval="" SpringMode="" ResponseMode="" />
    </Object>
    <Object Guid="7BCF22BB9A3E43FA83561274A000814E" Desc="厨师康达尔" config="npc_zlm001_0093" Layer="" MaxRefreshCount="" x="-3666.850586" y="15.699524" z="7460.173828" IsY="0" Radius="0.1" UseSuicideTime="" PeaceAction="" PathID="" amount="1" RefreshMode="" RefreshPointSet="" RefreshTime="1" sx="" sy="" sz="" fOrg="0.395" PatrolMode="" RoadSignID="">
        <Task Issue="" Refer="" />
        <OrganData IsOrgan="" Controllers="" IniState="" AutoResume="" ResumeState="" ResumeInterval="" SpringMode="" ResponseMode="" />
    </Object>
    <Object Guid="8C1295B9B77C42509AF8A8E672B1E7C2" Desc="探索队队长萨姆尔" config="npc_zlm001_0051" Layer="" MaxRefreshCount="" x="-3009.294434" y="31.706337" z="6592.322266" IsY="0" Radius="0.1" UseSuicideTime="" PeaceAction="" PathID="" amount="1" RefreshMode="" RefreshPointSet="" RefreshTime="1" sx="" sy="" sz="" fOrg="2.755" PatrolMode="" RoadSignID="">
        <Task Issue="" Refer="" />
        <OrganData IsOrgan="" Controllers="" IniState="" AutoResume="" ResumeState="" ResumeInterval="" SpringMode="" ResponseMode="" />
    </Object>
    <Object Guid="60EFFE1E9E4C4BD9B8AC1D4137250EA3" Desc="探索队员西欧多尔" config="npc_zlm001_0053" Layer="" MaxRefreshCount="" x="-2993.771729" y="24.036022" z="6535.172363" IsY="0" Radius="0.1" UseSuicideTime="" PeaceAction="" PathID="" amount="1" RefreshMode="" RefreshPointSet="" RefreshTime="1" sx="" sy="" sz="" fOrg="0" PatrolMode="" RoadSignID="">
        <Task Issue="" Refer="" />
        <OrganData IsOrgan="" Controllers="" IniState="" AutoResume="" ResumeState="" ResumeInterval="" SpringMode="" ResponseMode="" />
    </Object>
    <Object Guid="035AF98E1C5748B78582AB3104657098" Desc="学徒培匠达尔比" config="npc_zlm001_0094" Layer="" MaxRefreshCount="" x="-3021.25708" y="29.534264" z="6576.757813" IsY="0" Radius="0.1" UseSuicideTime="" PeaceAction="" PathID="" amount="1" RefreshMode="" RefreshPointSet="" RefreshTime="1" sx="" sy="" sz="" fOrg="0.22" PatrolMode="" RoadSignID="">
        <Task Issue="" Refer="" />
        <OrganData IsOrgan="" Controllers="" IniState="" AutoResume="" ResumeState="" ResumeInterval="" SpringMode="" ResponseMode="" />
    </Object>
    <Object Guid="FE5F039DA59043A18162113BB5566842" Desc="卫兵盖文" config="npc_zlm001_0052" Layer="" MaxRefreshCount="" x="-2982.504639" y="30.390223" z="6579.748535" IsY="0" Radius="0.1" UseSuicideTime="" PeaceAction="" PathID="" amount="1" RefreshMode="" RefreshPointSet="" RefreshTime="1" sx="" sy="" sz="" fOrg="5.685001" PatrolMode="" RoadSignID="">
        <Task Issue="" Refer="" />
        <OrganData IsOrgan="" Controllers="" IniState="" AutoResume="" ResumeState="" ResumeInterval="" SpringMode="" ResponseMode="" />
    </Object>
    <Object Guid="6498005B957D4BF49B619C3AE77B2E89" Desc="议员赛薇亚拉" config="npc_zlm001_0062" Layer="" MaxRefreshCount="" x="-2374.258789" y="31.112333" z="7154.786133" IsY="0" Radius="0.1" UseSuicideTime="" PeaceAction="" PathID="" amount="1" RefreshMode="" RefreshPointSet="" RefreshTime="1" sx="" sy="" sz="" fOrg="1.483182" PatrolMode="" RoadSignID="">
        <Task Issue="" Refer="" />
        <OrganData IsOrgan="" Controllers="" IniState="" AutoResume="" ResumeState="" ResumeInterval="" SpringMode="" ResponseMode="" />
    </Object>
    <Object Guid="F8792A908CD6465CB8F38D7DDEE33D65" Desc="研究员泰丽莎" config="npc_zlm001_0071" Layer="" MaxRefreshCount="" x="-2377.278564" y="31.138369" z="7157.080566" IsY="0" Radius="0.1" UseSuicideTime="" PeaceAction="" PathID="" amount="1" RefreshMode="" RefreshPointSet="" RefreshTime="1" sx="" sy="" sz="" fOrg="5.628185" PatrolMode="" RoadSignID="">
        <Task Issue="" Refer="" />
        <OrganData IsOrgan="" Controllers="" IniState="" AutoResume="" ResumeState="" ResumeInterval="" SpringMode="" ResponseMode="" />
    </Object>
    <Object Guid="EB2E404E36BD4EDF90F55F6DEABE61F0" Desc="灵智守护祭司安斯艾尔" config="npc_zlm001_0057" Layer="" MaxRefreshCount="" x="-2794.397949" y="44.380718" z="5991.56543" IsY="0" Radius="0.1" UseSuicideTime="" PeaceAction="" PathID="" amount="1" RefreshMode="" RefreshPointSet="" RefreshTime="1" sx="" sy="" sz="" fOrg="2.11" PatrolMode="" RoadSignID="">
        <Task Issue="" Refer="" />
        <OrganData IsOrgan="" Controllers="" IniState="" AutoResume="" ResumeState="" ResumeInterval="" SpringMode="" ResponseMode="" />
    </Object>
    <Object Guid="9AA7DA936DE248E4B617718C2FC19D27" Desc="灵智净化法师玛莉提丝" config="npc_zlm001_0058" Layer="" MaxRefreshCount="" x="-2791.056641" y="44.380718" z="5994.760742" IsY="0" Radius="0.1" UseSuicideTime="" PeaceAction="" PathID="" amount="1" RefreshMode="" RefreshPointSet="" RefreshTime="1" sx="" sy="" sz="" fOrg="2.305" PatrolMode="" RoadSignID="">
        <Task Issue="" Refer="" />
        <OrganData IsOrgan="" Controllers="" IniState="" AutoResume="" ResumeState="" ResumeInterval="" SpringMode="" ResponseMode="" />
    </Object>
    <Object Guid="6DF0A745C15843B6A4B06F3C46CC4F13" Desc="浓雾行者提奥巴斯" config="npc_zlm001_0055" Layer="" MaxRefreshCount="" x="-2791.4646" y="44.380817" z="5991.603516" IsY="0" Radius="0.1" UseSuicideTime="" PeaceAction="" PathID="" amount="1" RefreshMode="" RefreshPointSet="" RefreshTime="1" sx="" sy="" sz="" fOrg="1.875" PatrolMode="" RoadSignID="">
        <Task Issue="" Refer="" />
        <OrganData IsOrgan="" Controllers="" IniState="" AutoResume="" ResumeState="" ResumeInterval="" SpringMode="" ResponseMode="" />
    </Object>
    <Object Guid="865A74637AB04B11BB185F91FA0A342D" Desc="黑暗女王梅莉莎" config="npc_zlm001_0060" Layer="" MaxRefreshCount="" x="-2788.648926" y="43.372353" z="5954.23877" IsY="0" Radius="0.1" UseSuicideTime="" PeaceAction="" PathID="" amount="1" RefreshMode="" RefreshPointSet="" RefreshTime="1" sx="" sy="" sz="" fOrg="0.27" PatrolMode="" RoadSignID="">
        <Task Issue="" Refer="" />
        <OrganData IsOrgan="" Controllers="" IniState="" AutoResume="" ResumeState="" ResumeInterval="" SpringMode="" ResponseMode="" />
    </Object>
    <Object Guid="F1A9D15DD0E140459E570A425681882F" Desc="灵智守护祭司奥德里奇" config="npc_zlm001_0059" Layer="" MaxRefreshCount="" x="-2789.364258" y="43.425808" z="5955.702148" IsY="0" Radius="0.1" UseSuicideTime="" PeaceAction="" PathID="" amount="1" RefreshMode="" RefreshPointSet="" RefreshTime="1" sx="" sy="" sz="" fOrg="1.18" PatrolMode="" RoadSignID="">
        <Task Issue="" Refer="" />
        <OrganData IsOrgan="" Controllers="" IniState="" AutoResume="" ResumeState="" ResumeInterval="" SpringMode="" ResponseMode="" />
    </Object>
    <Object Guid="5050DF285BE547029AC533D896FC1259" Desc="药品商人艾德文娜" config="npc_zlm001_0026" Layer="" MaxRefreshCount="" x="-2831.111816" y="28.721439" z="7665.984863" IsY="0" Radius="0.1" UseSuicideTime="" PeaceAction="" PathID="" amount="1" RefreshMode="" RefreshPointSet="" RefreshTime="1" sx="" sy="" sz="" fOrg="0.745" PatrolMode="" RoadSignID="">
        <Task Issue="" Refer="" />
        <OrganData IsOrgan="" Controllers="" IniState="" AutoResume="" ResumeState="" ResumeInterval="" SpringMode="" ResponseMode="" />
    </Object>
    <Object Guid="51788BA702034F7EAEFA1FE03B34CFB2" Desc="镇魂猎手塞西尔" config="npc_zlm001_0065" Layer="" MaxRefreshCount="" x="-2820.587158" y="29.184397" z="7692.804199" IsY="0" Radius="0.1" UseSuicideTime="" PeaceAction="" PathID="" amount="1" RefreshMode="" RefreshPointSet="" RefreshTime="1" sx="" sy="" sz="" fOrg="1.2" PatrolMode="" RoadSignID="">
        <Task Issue="" Refer="" />
        <OrganData IsOrgan="" Controllers="" IniState="" AutoResume="" ResumeState="" ResumeInterval="" SpringMode="" ResponseMode="" />
    </Object>
    <Object Guid="2549A84014444123A1311B8A1850B5DA" Desc="驱魔师米兰达" config="npc_zlm001_0067" Layer="" MaxRefreshCount="" x="-2819.529297" y="29.203716" z="7695.030273" IsY="0" Radius="0.1" UseSuicideTime="" PeaceAction="" PathID="" amount="1" RefreshMode="" RefreshPointSet="" RefreshTime="1" sx="" sy="" sz="" fOrg="2.510001" PatrolMode="" RoadSignID="">
        <Task Issue="" Refer="" />
        <OrganData IsOrgan="" Controllers="" IniState="" AutoResume="" ResumeState="" ResumeInterval="" SpringMode="" ResponseMode="" />
    </Object>
    <Object Guid="25707E0D63814C70A3E90434F39FF915" Desc="镇魂祭司葛列格里" config="npc_zlm001_0064" Layer="" MaxRefreshCount="" x="-2779.744141" y="31.644812" z="7680.85498" IsY="0" Radius="0.1" UseSuicideTime="" PeaceAction="" PathID="" amount="1" RefreshMode="" RefreshPointSet="" RefreshTime="1" sx="" sy="" sz="" fOrg="4.05818" PatrolMode="" RoadSignID="">
        <Task Issue="" Refer="" />
        <OrganData IsOrgan="" Controllers="" IniState="" AutoResume="" ResumeState="" ResumeInterval="" SpringMode="" ResponseMode="" />
    </Object>
    <Object Guid="42C8B536DFB24A96B667D9013F99797D" Desc="邪魂猎手凯南" config="npc_zlm001_0056" Layer="" MaxRefreshCount="" x="-2781.048096" y="31.179144" z="7682.616211" IsY="0" Radius="0.1" UseSuicideTime="" PeaceAction="" PathID="" amount="1" RefreshMode="" RefreshPointSet="" RefreshTime="1" sx="" sy="" sz="" fOrg="4.043183" PatrolMode="" RoadSignID="">
        <Task Issue="" Refer="" />
        <OrganData IsOrgan="" Controllers="" IniState="" AutoResume="" ResumeState="" ResumeInterval="" SpringMode="" ResponseMode="" />
    </Object>
    <Object Guid="53F28A25AB074EB58D4FD19A50963E2C" Desc="镇魂巫师雷吉诺德" config="npc_zlm001_0063" Layer="" MaxRefreshCount="" x="-2779.523682" y="31.023458" z="7684.731445" IsY="0" Radius="0.1" UseSuicideTime="" PeaceAction="" PathID="" amount="1" RefreshMode="" RefreshPointSet="" RefreshTime="1" sx="" sy="" sz="" fOrg="3.903181" PatrolMode="" RoadSignID="">
        <Task Issue="" Refer="" />
        <OrganData IsOrgan="" Controllers="" IniState="" AutoResume="" ResumeState="" ResumeInterval="" SpringMode="" ResponseMode="" />
    </Object>
    <Object Guid="EA582E88394240F083D10D05DBE79B5F" Desc="亡语者西斯廷" config="npc_zlm001_0066" Layer="" MaxRefreshCount="" x="-2937.772461" y="21.963776" z="7608.260254" IsY="0" Radius="0.1" UseSuicideTime="" PeaceAction="" PathID="" amount="1" RefreshMode="" RefreshPointSet="" RefreshTime="1" sx="" sy="" sz="" fOrg="6.248185" PatrolMode="" RoadSignID="">
        <Task Issue="" Refer="" />
        <OrganData IsOrgan="" Controllers="" IniState="" AutoResume="" ResumeState="" ResumeInterval="" SpringMode="" ResponseMode="" />
    </Object>
    <Object Guid="BC5608D891DE43A0BE5B01E00601B5A7" Desc="侦查员欧尼斯特" config="npc_zlm001_0070" Layer="" MaxRefreshCount="" x="-2517.102295" y="26.918522" z="7306.717285" IsY="0" Radius="0.1" UseSuicideTime="" PeaceAction="" PathID="" amount="1" RefreshMode="" RefreshPointSet="" RefreshTime="1" sx="" sy="" sz="" fOrg="2.535001" PatrolMode="" RoadSignID="">
        <Task Issue="" Refer="" />
        <OrganData IsOrgan="" Controllers="" IniState="" AutoResume="" ResumeState="" ResumeInterval="" SpringMode="" ResponseMode="" />
    </Object>
    <Object Guid="D8AAC6E257AE40AE969A8C0B76427B9C" Desc="" config="npc_zlm001_0069" Layer="" MaxRefreshCount="" x="-2377.42334" y="31.121204" z="7151.113281" IsY="0" Radius="0.1" UseSuicideTime="" PeaceAction="" PathID="" amount="1" RefreshMode="" RefreshPointSet="" RefreshTime="1" sx="" sy="" sz="" fOrg="3.393183" PatrolMode="" RoadSignID="">
        <Task Issue="" Refer="" />
        <OrganData IsOrgan="" Controllers="" IniState="" AutoResume="" ResumeState="" ResumeInterval="" SpringMode="" ResponseMode="" />
    </Object>
    <Object Guid="1EAD70F6AC504C5F8F14FD53782DFBE7" Desc="" config="npc_zlm001_0061" Layer="" MaxRefreshCount="" x="-2378.442627" y="31.129366" z="7149.444336" IsY="0" Radius="0.1" UseSuicideTime="" PeaceAction="" PathID="" amount="1" RefreshMode="" RefreshPointSet="" RefreshTime="1" sx="" sy="" sz="" fOrg="0.450001" PatrolMode="" RoadSignID="">
        <Task Issue="" Refer="" />
        <OrganData IsOrgan="" Controllers="" IniState="" AutoResume="" ResumeState="" ResumeInterval="" SpringMode="" ResponseMode="" />
    </Object>
    <Object Guid="4B2DA2E918674F4BA6C513000DBB32A4" Desc="" config="npc_zlm001_0068" Layer="" MaxRefreshCount="" x="-2372.248291" y="31.037292" z="7154.680176" IsY="0" Radius="0.1" UseSuicideTime="" PeaceAction="" PathID="" amount="1" RefreshMode="" RefreshPointSet="" RefreshTime="1" sx="" sy="" sz="" fOrg="4.813191" PatrolMode="" RoadSignID="">
        <Task Issue="" Refer="" />
        <OrganData IsOrgan="" Controllers="" IniState="" AutoResume="" ResumeState="" ResumeInterval="" SpringMode="" ResponseMode="" />
    </Object>
    <Object Guid="6334CFEBAE0D44A183A3F23F3B649ACF" Desc="" config="npc_zlm001_0072" Layer="" MaxRefreshCount="" x="-3041.483398" y="35.661766" z="6623.295898" IsY="0" Radius="0.1" UseSuicideTime="" PeaceAction="" PathID="" amount="1" RefreshMode="" RefreshPointSet="" RefreshTime="1" sx="" sy="" sz="" fOrg="3.418184" PatrolMode="" RoadSignID="">
        <Task Issue="" Refer="" />
        <OrganData IsOrgan="" Controllers="" IniState="" AutoResume="" ResumeState="" ResumeInterval="" SpringMode="" ResponseMode="" />
        <Event EventId="0" EventIndex="0" Processor="11103102432909" />
        <Event EventId="14" EventIndex="14" Processor="11112420195816" />
    </Object>
    <Object Guid="2F5E23BC414B4FD2A202679B592CE2C4" Desc="普通的亡语者" config="npc_zlm001_0102" Layer="" MaxRefreshCount="" x="-2412.034912" y="70.62149" z="6104.399902" IsY="0" Radius="0.1" UseSuicideTime="" PeaceAction="" PathID="" amount="1" RefreshMode="" RefreshPointSet="" RefreshTime="1" sx="" sy="" sz="" fOrg="5.788185" PatrolMode="" RoadSignID="">
        <Task Issue="" Refer="" />
        <OrganData IsOrgan="" Controllers="" IniState="" AutoResume="" ResumeState="" ResumeInterval="" SpringMode="" ResponseMode="" />
    </Object>
    <Object Guid="A1F4354E23FB401994D1F2292B323822" Desc="" config="npc_zlm001_0054" Layer="" MaxRefreshCount="" x="-3543.035645" y="17.646318" z="6627.972168" IsY="0" Radius="0.1" UseSuicideTime="" PeaceAction="" PathID="" amount="1" RefreshMode="" RefreshPointSet="" RefreshTime="1" sx="" sy="" sz="" fOrg="2.695" PatrolMode="" RoadSignID="">
        <Task Issue="" Refer="" />
        <OrganData IsOrgan="" Controllers="" IniState="" AutoResume="" ResumeState="" ResumeInterval="" SpringMode="" ResponseMode="" />
     
    </Object>
</Stage>
