<?xml version="1.0" encoding="gb2312"?>
<!-- 编辑使用 XMLSpy v2006 U (http://www.altova.com) 由 any (any) -->
<Object>
	<Property ID="5"/>
	<Property ID="329191" HitShape="3" HitShapePara2="4" HitShapePara3="1" HitShapePara1="70"/>
	<Property ID="325302" HitShape="6" HitShapePara2="2" HitShapePara3="2"/>
	<Property ID="325303" HitShape="6" HitShapePara2="2" HitShapePara3="3"/>
	<Property ID="325304" HitShape="6" HitShapePara2="2" HitShapePara3="4"/>
	<Property ID="325305" HitShape="6" HitShapePara2="2" HitShapePara3="5"/>
	<Property ID="325306" HitShape="6" HitShapePara2="2" HitShapePara3="6"/>
	<Property ID="325307" HitShape="6" HitShapePara2="2" HitShapePara3="7"/>
	<Property ID="325308" HitShape="6" HitShapePara2="2" HitShapePara3="8"/>
	<Property ID="326151" Name="复苏之风" HitShape="10" HitShapePara1="3" HitShapePara2="7" HitShapePara3="6"/>
	<Property ID="326152" Name="复苏之风" HitShape="10" HitShapePara1="3" HitShapePara2="3" HitShapePara3="10"/>
</Object>


