<?xml version="1.0" encoding="gb2312"?>
<!-- 编辑使用 XMLSpy v2006 U (http://www.altova.com) 由 any (any) -->
<!-- 编辑使用 XMLSpy v2006 U (http://www.altova.com) 由 any (any) -->
<!-- 编辑使用 XMLSpy v2006 U (http://www.altova.com) 由 any (any) -->
<!-- 编辑使用 XMLSpy v2006 U (http://www.altova.com) 由 any (any) -->
<!-- 编辑使用 XMLSpy v2006 U (http://www.altova.com) 由 any (any) -->
<Object>
	<Property ID="1" Comment="清除免疫（类型，0增益）" type="1" value="0"/>
	<Property ID="2" Comment="清除免疫（类型，1减益）" type="1" value="1"/>
	<Property ID="3" Comment="清除免疫99997(根据BUFF编号）" type="2" value="99997"/>
	<Property ID="4" Comment="免疫眩晕" type="3" value="Buff_Status001_01"/>
	<Property ID="5" Comment="免疫沉默" type="3" value="Buff_Status002_01"/>
	<Property ID="6" Comment="免疫麻痹" type="3" value="Buff_Status003_01"/>
	<Property ID="7" Comment="免疫缠绕" type="3" value="Buff_Status005_01"/>
	<Property ID="8" Comment="免疫石化" type="3" value="Buff_Status006_01"/>
	<Property ID="9" Comment="免疫昏迷" type="3" value="Buff_Status007_01"/>
	<Property ID="10" Comment="免疫冰冻" type="3" value="Buff_Status008_01"/>
	<Property ID="11" Comment="免疫禁锢" type="3" value="Buff_Status009_01"/>
	<Property ID="12" Comment="免疫嘲讽" type="3" value="Buff_Status010_01"/>
	<Property ID="13" Comment="免疫沉睡" type="3" value="Buff_Status013_01"/>
	<Property ID="14" Comment="免疫变形术1级" type="3" value="Buff_Wm2703_01_1"/>
	<Property ID="15" Comment="免疫变形术2级" type="3" value="Buff_Wm2703_02_1"/>
	<Property ID="16" Comment="免疫变形术3级" type="3" value="Buff_Wm2703_03_1"/>
	<Property ID="17" Comment="免疫变形术4级" type="3" value="Buff_Wm2703_04_1"/>
	<Property ID="18" Comment="免疫变形术5级" type="3" value="Buff_Wm2703_05_1"/>
	<Property ID="19" Comment="免疫变形术6级" type="3" value="Buff_Wm2703_06_1"/>
	<Property ID="20" Comment="免疫僵直" type="3" value="CorpseTime_Buff01_01"/>
	<Property ID="21" Comment="免疫器灵限制BUFF" type="3" value="Buff_Bm3030_01_10"/>
	<Property ID="22" Comment="免疫宁静沉默" type="3" value="Buff_Em2614_01_2"/>
	<Property ID="23" Comment="免疫副本BOSS减益BUFF" type="3" value="Buff_boss_0106_05"/>
	<Property ID="24" Comment="免疫副本BOSS减益BUFF" type="3" value="Buff_boss_0004_03"/>
	<Property ID="25" Comment="免疫副本BOSS减益BUFF" type="3" value="Buff_boss_0122_01"/>
	<Property ID="26" Comment="免疫副本BOSS减益BUFF" type="3" value="Buff_Boss_0129_01"/>
	<Property ID="27" Comment="免疫副本BOSS减益BUFF" type="3" value="Buff_Boss_0026_02_01"/>
	<Property ID="28" Comment="免疫副本BOSS减益BUFF" type="3" value="Buff_FB_YGZM_Hbr0013_1"/>
	<Property ID="29" Comment="免疫副本BOSS减益BUFF" type="3" value="buff_fb_chnj_npc_01"/>
	<Property ID="30" Comment="免疫副本BOSS减益BUFF" type="3" value="buff_fb_chnj_npc_02"/>
	<Property ID="31" Comment="免疫副本BOSS减益BUFF" type="3" value="Buff_FB_YHDX_0010_01"/>
</Object>
