<?xml version="1.0" encoding="gb2312"?>
<Object>

<Property ID="0" Level="1" exp="5"/>
<Property ID="1" Level="2" exp="10"/>
<Property ID="2" Level="3" exp="15"/>
<Property ID="3" Level="4" exp="20"/>
<Property ID="4" Level="5" exp="25"/>
<Property ID="5" Level="6" exp="30"/>
<Property ID="6" Level="7" exp="35"/>
<Property ID="7" Level="8" exp="40"/>
<Property ID="8" Level="9" exp="45"/>
<Property ID="9" Level="10" exp="50"/>
<Property ID="10" Level="11" exp="55"/>
<Property ID="11" Level="12" exp="60"/>
<Property ID="12" Level="13" exp="65"/>
<Property ID="13" Level="14" exp="70"/>
<Property ID="14" Level="15" exp="75"/>
<Property ID="15" Level="16" exp="80"/>
<Property ID="16" Level="17" exp="85"/>
<Property ID="17" Level="18" exp="90"/>
<Property ID="18" Level="19" exp="95"/>
<Property ID="19" Level="20" exp="100"/>
<Property ID="20" Level="21" exp="105"/>
<Property ID="21" Level="22" exp="110"/>
<Property ID="22" Level="23" exp="115"/>
<Property ID="23" Level="24" exp="120"/>
<Property ID="24" Level="25" exp="125"/>
<Property ID="25" Level="26" exp="130"/>
<Property ID="26" Level="27" exp="135"/>
<Property ID="27" Level="28" exp="140"/>
<Property ID="28" Level="29" exp="145"/>
<Property ID="29" Level="30" exp="150"/>
<Property ID="30" Level="31" exp="155"/>
<Property ID="31" Level="32" exp="160"/>
<Property ID="32" Level="33" exp="165"/>
<Property ID="33" Level="34" exp="170"/>
<Property ID="34" Level="35" exp="175"/>
<Property ID="35" Level="36" exp="180"/>
<Property ID="36" Level="37" exp="185"/>
<Property ID="37" Level="38" exp="190"/>
<Property ID="38" Level="39" exp="195"/>
<Property ID="39" Level="40" exp="200"/>
<Property ID="40" Level="41" exp="205"/>
<Property ID="41" Level="42" exp="210"/>
<Property ID="42" Level="43" exp="215"/>
<Property ID="43" Level="44" exp="220"/>
<Property ID="44" Level="45" exp="225"/>
<Property ID="45" Level="46" exp="230"/>
<Property ID="46" Level="47" exp="235"/>
<Property ID="47" Level="48" exp="240"/>
<Property ID="48" Level="49" exp="245"/>
<Property ID="49" Level="50" exp="250"/>
<Property ID="50" Level="51" exp="255"/>
<Property ID="51" Level="52" exp="260"/>
<Property ID="52" Level="53" exp="265"/>
<Property ID="53" Level="54" exp="270"/>
<Property ID="54" Level="55" exp="275"/>
<Property ID="55" Level="56" exp="280"/>
<Property ID="56" Level="57" exp="285"/>
<Property ID="57" Level="58" exp="290"/>
<Property ID="58" Level="59" exp="295"/>
<Property ID="59" Level="60" exp="300"/>
<Property ID="60" Level="61" exp="305"/>

</Object>
