<?xml version="1.0" encoding="gb2312"?>
<!-- 编辑使用 XMLSpy v2006 U (http://www.altova.com) 由 any (any) -->
<!-- 编辑使用 XMLSpy v2006 U (http://www.altova.com) 由 any (any) -->
<Object>
	<Property ID="20001" GirdX="1" GirdY="2" FatherTask="" ChildTask="20002" IsHide="1" LastTask=""/>
	<Property ID="20002" GirdX="2" GirdY="2" FatherTask="20001" ChildTask="20003" IsHide="1" LastTask=""/>
	<Property ID="20003" GirdX="3" GirdY="2" FatherTask="20002" ChildTask="20004" IsHide="1" LastTask=""/>
	<Property ID="20004" GirdX="4" GirdY="2" FatherTask="20003" ChildTask="20005" IsHide="1" LastTask=""/>
	<Property ID="20005" GirdX="5" GirdY="2" FatherTask="20004" ChildTask="20006" IsHide="1" LastTask=""/>
	<Property ID="20006" GirdX="6" GirdY="2" FatherTask="20005" ChildTask="20007" IsHide="1" LastTask=""/>
	<Property ID="20007" GirdX="7" GirdY="2" FatherTask="20006" ChildTask="20008" IsHide="1" LastTask=""/>
	<Property ID="20008" GirdX="8" GirdY="2" FatherTask="20007" ChildTask="20009" IsHide="1" LastTask=""/>
	<Property ID="20009" GirdX="9" GirdY="2" FatherTask="20008" ChildTask="20010" IsHide="1" LastTask=""/>
	<Property ID="20010" GirdX="10" GirdY="2" FatherTask="20009" ChildTask="20011" IsHide="1" LastTask=""/>
	<Property ID="20011" GirdX="11" GirdY="2" FatherTask="20010" ChildTask="20012" IsHide="1" LastTask=""/>
	<Property ID="20012" GirdX="12" GirdY="2" FatherTask="20011" ChildTask="20013" IsHide="1" LastTask=""/>
	<Property ID="20013" GirdX="13" GirdY="2" FatherTask="20012" ChildTask="20014" IsHide="1" LastTask=""/>
	<Property ID="20014" GirdX="14" GirdY="2" FatherTask="20013" ChildTask="20015" IsHide="1" LastTask=""/>
	<Property ID="20015" GirdX="15" GirdY="2" FatherTask="20014" ChildTask="20016" IsHide="1" LastTask=""/>
	<Property ID="20016" GirdX="16" GirdY="2" FatherTask="20015" ChildTask="20017" IsHide="1" LastTask=""/>
	<Property ID="20017" GirdX="17" GirdY="2" FatherTask="20016" ChildTask="20018" IsHide="1" LastTask=""/>
	<Property ID="20018" GirdX="18" GirdY="2" FatherTask="20017" ChildTask="20019" IsHide="1" LastTask=""/>
	<Property ID="20019" GirdX="19" GirdY="2" FatherTask="20018" ChildTask="20020" IsHide="1" LastTask=""/>
	<Property ID="20020" GirdX="20" GirdY="2" FatherTask="20019" ChildTask="20021" IsHide="1" LastTask=""/>
	<Property ID="20021" GirdX="21" GirdY="2" FatherTask="20020" ChildTask="20022" IsHide="1" LastTask=""/>
	<Property ID="20022" GirdX="22" GirdY="2" FatherTask="20021" ChildTask="20023" IsHide="1" LastTask=""/>
	<Property ID="20023" GirdX="23" GirdY="2" FatherTask="20022" ChildTask="20024" IsHide="1" LastTask=""/>
	<Property ID="20024" GirdX="24" GirdY="2" FatherTask="20023" ChildTask="20025" IsHide="1" LastTask=""/>
	<Property ID="20025" GirdX="25" GirdY="2" FatherTask="20024" ChildTask="20026" IsHide="1" LastTask=""/>
	<Property ID="20026" GirdX="26" GirdY="2" FatherTask="20025" ChildTask="20027" IsHide="1" LastTask=""/>
	<Property ID="20027" GirdX="27" GirdY="2" FatherTask="20026" ChildTask="20028" IsHide="1" LastTask=""/>
	<Property ID="20028" GirdX="28" GirdY="2" FatherTask="20027" ChildTask="20029" IsHide="1" LastTask=""/>
	<Property ID="20029" GirdX="29" GirdY="2" FatherTask="20028" ChildTask="20030" IsHide="1" LastTask=""/>
	<Property ID="20030" GirdX="30" GirdY="2" FatherTask="20029" ChildTask="20031" IsHide="1" LastTask=""/>
	<Property ID="20031" GirdX="31" GirdY="2" FatherTask="20030" ChildTask="20032" IsHide="1" LastTask=""/>
	<Property ID="20032" GirdX="32" GirdY="2" FatherTask="20031" ChildTask="20033" IsHide="1" LastTask=""/>
	<Property ID="20033" GirdX="33" GirdY="2" FatherTask="20032" ChildTask="20034" IsHide="1" LastTask=""/>
	<Property ID="20034" GirdX="34" GirdY="2" FatherTask="20033" ChildTask="20035" IsHide="1" LastTask=""/>
	<Property ID="20035" GirdX="35" GirdY="2" FatherTask="20034" ChildTask="20036" IsHide="1" LastTask=""/>
	<Property ID="20036" GirdX="36" GirdY="2" FatherTask="20035" ChildTask="20037" IsHide="1" LastTask=""/>
	<Property ID="20037" GirdX="37" GirdY="2" FatherTask="20036" ChildTask="20038" IsHide="1" LastTask=""/>
	<Property ID="20038" GirdX="38" GirdY="2" FatherTask="20037" ChildTask="20039" IsHide="1" LastTask=""/>
	<Property ID="20039" GirdX="39" GirdY="2" FatherTask="20038" ChildTask="20040" IsHide="1" LastTask=""/>
	<Property ID="20040" GirdX="40" GirdY="2" FatherTask="20039" ChildTask="20041" IsHide="1" LastTask=""/>
	<Property ID="20041" GirdX="41" GirdY="2" FatherTask="20040" ChildTask="20042" IsHide="1" LastTask=""/>
	<Property ID="20042" GirdX="42" GirdY="2" FatherTask="20041" ChildTask="20043" IsHide="1" LastTask=""/>
	<Property ID="20043" GirdX="43" GirdY="2" FatherTask="20042" ChildTask="20044" IsHide="1" LastTask=""/>
	<Property ID="20044" GirdX="44" GirdY="2" FatherTask="20043" ChildTask="20045" IsHide="1" LastTask=""/>
	<Property ID="20045" GirdX="45" GirdY="2" FatherTask="20044" ChildTask="20046" IsHide="1" LastTask=""/>
	<Property ID="20046" GirdX="46" GirdY="2" FatherTask="20045" ChildTask="20047" IsHide="1" LastTask=""/>
	<Property ID="20047" GirdX="47" GirdY="2" FatherTask="20046" ChildTask="20048" IsHide="1" LastTask=""/>
	<Property ID="20048" GirdX="48" GirdY="2" FatherTask="20047" ChildTask="20049" IsHide="1" LastTask=""/>
	<Property ID="20049" GirdX="49" GirdY="2" FatherTask="20048" ChildTask="20050" IsHide="1" LastTask=""/>
	<Property ID="20050" GirdX="50" GirdY="2" FatherTask="20049" ChildTask="20051" IsHide="1" LastTask=""/>
	<Property ID="20051" GirdX="51" GirdY="2" FatherTask="20050" ChildTask="" IsHide="1" LastTask="1"/>
</Object>
