<?xml version="1.0" encoding="gb2312"?>
<Stage>
	<Object Guid="7A965A1E1D084B1FA57149CC6FF1D092" Desc="FB_TNJT_MS_06" config="FB_TNJT_MS_06" x="244.608124" y="58.026001" z="-234.413467" amount="1" fOrg="0" IsPersistent="0" RefreshTime="-1"/>
	<Object Guid="E0CA230B5C244003A157F359B3481436" Desc="FB_TNJT_MS_06" config="FB_TNJT_MS_06" x="244.094894" y="57.989124" z="-232.959885" amount="1" fOrg="1.725003" IsPersistent="0" RefreshTime="-1"/>
	<Object Guid="DA541A4E5E1945B9B50D8FB3E82C30C3" Desc="FB_TNJT_MS_09" config="FB_TNJT_MS_09" x="236.689392" y="58.000107" z="-236.114716" amount="1" fOrg="-2.130012" IsPersistent="0" RefreshTime="-1"/>
	<Object Guid="38D96E7047F949029C1EA672D951C612" Desc="FB_TNJT_MS_09" config="FB_TNJT_MS_09" x="236.371704" y="58.026001" z="-234.354538" amount="1" fOrg="0" IsPersistent="0" RefreshTime="-1"/>
	<Object Guid="43C59565F4994CA29D97E189B0EA91EA" Desc="FB_TNJT_MS_06" config="FB_TNJT_MS_06" x="248.543884" y="58.026001" z="-242.822067" amount="1" fOrg="2.264999" IsPersistent="0" RefreshTime="-1"/>
	<Object Guid="E9101327039C4DFDB5D8AB982921229A" Desc="FB_TNJT_MS_06" config="FB_TNJT_MS_06" x="249.409637" y="58.026001" z="-245.557083" amount="1" fOrg="-2.355004" IsPersistent="0" RefreshTime="-1"/>
	<Object Guid="C9D06837FD1D4813BC6E67F6801BEFB3" Desc="FB_TNJT_MS_09" config="FB_TNJT_MS_09" x="247.477615" y="57.981945" z="-244.924484" amount="1" fOrg="0.54" IsPersistent="0" RefreshTime="-1"/>
	<Object Guid="B51E909665414EA79413F7AD11C4D269" Desc="FB_TNJT_MS_06" config="FB_TNJT_MS_06" x="238.703827" y="57.995693" z="-244.091873" amount="1" fOrg="0" IsPersistent="0" RefreshTime="-1"/>
	<Object Guid="784EC3D7774C4E8CA3314BF7A0A6DDC6" Desc="FB_TNJT_BOSS_04" config="FB_TNJT_BOSS_04" x="413.967255" y="80.527336" z="-249.040024" amount="1" fOrg="-1.700002" IsPersistent="0" RefreshTime="-1"/>
	<Object Guid="FBD1CB7BF03840EA969F5505B77DEB03" Desc="FB_TNJT_MS_03" config="FB_TNJT_MS_03" x="399.699951" y="76.246964" z="-247.04361" amount="1" fOrg="-2.365001" IsPersistent="0" RefreshTime="-1"/>
	<Object Guid="865B1BE8A97F4402A3A1701084C6379E" Desc="FB_TNJT_MS_03" config="FB_TNJT_MS_03" x="405.882111" y="76.236229" z="-261.796783" amount="1" fOrg="-1.680004" IsPersistent="0" RefreshTime="-1"/>
	<Object Guid="ECB14EA2EC08421B8BF621B5550228C7" Desc="末日教护教骑士" config="FB_TNJT_MS_02" x="232.416931" y="58.026001" z="-222.447952" amount="1" fOrg="0" IsPersistent="0" RefreshTime="-1"/>
	<Object Guid="3274BF1B94DD414CB981468150B4E4A9" Desc="末日教护教骑士" config="FB_TNJT_MS_02" x="227.701691" y="58.026001" z="-224.673706" amount="1" fOrg="0" IsPersistent="0" RefreshTime="-1"/>
	<Object Guid="FEFC8AD8C4B7404F9528AAC84F9153F5" Desc="FB_TNJT_NPC_04" config="FB_TNJT_NPC_04" x="119.288185" y="35.293003" z="-166.514297" amount="1" fOrg="0" IsPersistent="0" RefreshTime="-1"/>
	<Object Guid="71A40711D6D7421F9172BFBB31A2C958" Desc="喷火机关" config="FB_TNJT_NPC_03" x="98.149307" y="32.122002" z="-166.97998" amount="1" fOrg="0.625001" IsPersistent="0" RefreshTime="-1"/>
	<Object Guid="E288A9DCAA654DC8A3D14F5793729E10" Desc="喷火机关" config="FB_TNJT_NPC_03" x="134.356415" y="38.747841" z="-170.260208" amount="1" fOrg="0.435001" IsPersistent="0" RefreshTime="-1"/>
	<Object Guid="AEE1182BA0B44260934BFDCBB94FDA5D" Desc="FB_TNJT_NPC_04" config="FB_TNJT_NPC_04" x="201.567413" y="50.283001" z="-183.528656" amount="1" fOrg="0" IsPersistent="0" RefreshTime="-1"/>
	<Object Guid="4E8709508993444B8D81720F6AB3AD9E" Desc="喷火机关" config="FB_TNJT_NPC_03" x="217.764145" y="57.015003" z="-191.964401" amount="1" fOrg="0.925024" IsPersistent="0" RefreshTime="-1"/>
	<Object Guid="F5232FB766F44A09A8C5337568969A11" Desc="FB_TNJT_NPC_04" config="FB_TNJT_NPC_04" x="170.439987" y="42.936001" z="-177.838715" amount="1" fOrg="0" IsPersistent="0" RefreshTime="-1"/>
	<Object Guid="54F9207E8F7D47A599CBC1D278DFE19B" Desc="喷火机关" config="FB_TNJT_NPC_03" x="187.264343" y="47.533619" z="-172.667496" amount="1" fOrg="-2.728182" IsPersistent="0" RefreshTime="-1"/>
	<Object Guid="80BA9D084D1741738A70D0036DA865A5" Desc="喷火机关" config="FB_TNJT_NPC_03" x="157.502884" y="41.826" z="-177.802917" amount="1" fOrg="-2.593181" IsPersistent="0" RefreshTime="-1"/>
	<Object Guid="2397E8281A534B358F2BC78962DEC492" Desc="末日教长" config="FB_TNJT_BOSS_02" x="299.736145" y="57.994419" z="-377.215851" PeaceAction="attack4" amount="1" fOrg="0" IsPersistent="0" RefreshTime="-1"/>
	<Object Guid="8268233B86A140D5A5A3788B928F2C69" Desc="FB_TNJT_MS_13" config="FB_TNJT_MS_13" x="306.137024" y="76.014" z="-294.154083" amount="1" fOrg="-2.505001" IsPersistent="0" RefreshTime="-1"/>
	<Object Guid="2C9BC12E75AB4699B45D5E4D2E06A208" Desc="FB_TNJT_MS_13" config="FB_TNJT_MS_13" x="313.047028" y="76.014" z="-297.254974" amount="1" fOrg="-1.605008" IsPersistent="0" RefreshTime="-1"/>
	<Object Guid="CA81A55B91664E7C8772068B142A0D3C" Desc="FB_TNJT_MS_11" config="FB_TNJT_MS_11" x="315.793854" y="76.011002" z="-290.015106" amount="1" fOrg="1.560003" IsPersistent="0" RefreshTime="-1"/>
	<Object Guid="A08885EC9815487ABA17A90CEB15215A" Desc="FB_TNJT_MS_11" config="FB_TNJT_MS_11" x="308.829803" y="76.014" z="-298.228821" amount="1" fOrg="0.945002" IsPersistent="0" RefreshTime="-1"/>
	<Object Guid="E866245756834D26A715DE793C04ADDC" Desc="FB_TNJT_MS_11" config="FB_TNJT_MS_11" x="308.158875" y="76.095001" z="-287.087524" amount="1" fOrg="-2.839998" IsPersistent="0" RefreshTime="-1"/>
	<Object Guid="76EE5DF6208945819D2301B1F6C36DF9" Desc="FB_TNJT_MS_12" config="FB_TNJT_MS_12" x="303.474854" y="75.867004" z="-293.361816" amount="1" fOrg="2.405003" IsPersistent="0" RefreshTime="-1"/>
	<Object Guid="653D7A11A63F414483655FA8A1B68A49" Desc="FB_TNJT_MS_12" config="FB_TNJT_MS_12" x="306.449738" y="76.020004" z="-290.837555" amount="1" fOrg="0" IsPersistent="0" RefreshTime="-1"/>
	<Object Guid="3BF01060734746A0AE54B5BF9FA7E6A5" Desc="FB_TNJT_MS_13" config="FB_TNJT_MS_13" x="318.484406" y="76.005005" z="-295.133179" amount="1" fOrg="-1.795004" IsPersistent="0" RefreshTime="-1"/>
	<Object Guid="CA0D387A286C49808B95BD6D0B053CA3" Desc="FB_TNJT_MS_13" config="FB_TNJT_MS_13" x="312.262054" y="76.017006" z="-289.307648" amount="1" fOrg="0" IsPersistent="0" RefreshTime="-1"/>
	<Object Guid="F78322C61AF44241A25EDC8D7B751A85" Desc="FB_TNJT_MS_12" config="FB_TNJT_MS_12" x="318.487366" y="76.008003" z="-291.153503" amount="1" fOrg="-1.285003" IsPersistent="0" RefreshTime="-1"/>
	<Object Guid="CAA3BB761A9140B4B4F05986D933D37D" Desc="FB_TNJT_MS_12" config="FB_TNJT_MS_12" x="305.725586" y="76.101006" z="-288.214813" amount="1" fOrg="1.860004" IsPersistent="0" RefreshTime="-1"/>
	<Object Guid="EFC11B2088CE41AA9A9CA641D484CDBB" Desc="FB_TNJT_MS_11" config="FB_TNJT_MS_11" x="310.779907" y="76.017006" z="-295.687469" amount="1" fOrg="2.660004" IsPersistent="0" RefreshTime="-1"/>
	<Object Guid="F40192E9754543DAA803520B502DE554" Desc="FB_TNJT_MS_11" config="FB_TNJT_MS_11" x="305.028412" y="76.011002" z="-296.723175" amount="1" fOrg="-0.630001" IsPersistent="0" RefreshTime="-1"/>
	<Object Guid="19A5F7AE3ECD41BB93B7C954633C2DA5" Desc="FB_TNJT_MS_12" config="FB_TNJT_MS_12" x="311.202362" y="76.017006" z="-286.591888" amount="1" fOrg="1.175001" IsPersistent="0" RefreshTime="-1"/>
	<Object Guid="8B2FFEFB98EC435FA5C890D8E87A70A9" Desc="FB_TNJT_MS_11" config="FB_TNJT_MS_11" x="309.006989" y="76.020004" z="-290.048981" amount="1" fOrg="-0.870002" IsPersistent="0" RefreshTime="-1"/>
	<Object Guid="A7C18D365DFB485BACD2D3AA93B8B16C" Desc="FB_TNJT_MS_11" config="FB_TNJT_MS_11" x="311.442352" y="76.107002" z="-299.141724" amount="1" fOrg="0" IsPersistent="0" RefreshTime="-1"/>
	<Object Guid="46085217E76144CEB81CD58FB25F79BB" Desc="FB_TNJT_MS_11" config="FB_TNJT_MS_11" x="315.949036" y="76.011002" z="-294.318207" amount="1" fOrg="2.028185" IsPersistent="0" RefreshTime="-1"/>
	<Object Guid="D383D2C87ABD410EB83125E9FA82F748" Desc="FB_TNJT_MS_13" config="FB_TNJT_MS_13" x="318.170685" y="76.008003" z="-288.244293" amount="1" fOrg="-2.869999" IsPersistent="0" RefreshTime="-1"/>
	<Object Guid="2090D684887D470A86081E52919F6192" Desc="FB_TNJT_MS_12" config="FB_TNJT_MS_12" x="313.685333" y="76.047005" z="-285.408173" amount="1" fOrg="2.34001" IsPersistent="0" RefreshTime="-1"/>
	<Object Guid="B169F0F1AEC84ECEBF6AB183D762E848" Desc="FB_TNJT_MS_12" config="FB_TNJT_MS_12" x="316.09079" y="76.014" z="-296.926941" amount="1" fOrg="0" IsPersistent="0" RefreshTime="-1"/>
	<Object Guid="E2605ACD2497486595BDCFE005E033E8" Desc="末日教士" config="FB_TNJT_MS_06" x="223.589783" y="37.233574" z="-317.245911" amount="1" fOrg="0" StartIndexNo="1" IsPersistent="0" RefreshTime="-1">
		<Event EventId="5" Processor="FB_TNJT_023"/>
	</Object>
	<Object Guid="D080417D648141DB80B64024FC02159A" Desc="末日教士" config="FB_TNJT_MS_06" x="211.80571" y="36.599491" z="-320.869324" amount="1" fOrg="0" IsPersistent="0" RefreshTime="-1">
		<Event EventId="5" Processor="FB_TNJT_023"/>
	</Object>
	<Object Guid="6682C7B6678A4305A34A781BA4B753EF" Desc="末日教士" config="FB_TNJT_MS_06" x="214.667984" y="36.675907" z="-320.212494" amount="1" fOrg="0" IsPersistent="0" RefreshTime="-1">
		<Event EventId="5" Processor="FB_TNJT_023"/>
	</Object>
	<Object Guid="79D65307719945DAADEFA850AE024DDB" Desc="末日教护教骑士" config="FB_TNJT_MS_02" x="204.09996" y="36.831703" z="-327.915802" amount="1" fOrg="0" IsPersistent="0" RefreshTime="-1">
		<Event EventId="5" Processor="FB_TNJT_023"/>
	</Object>
	<Object Guid="6E41418DBF7849D69DDD826B645F96C3" Desc="末日教护教骑士" config="FB_TNJT_MS_02" x="208.805054" y="36.437962" z="-328.033295" amount="1" fOrg="0" IsPersistent="0" RefreshTime="-1">
		<Event EventId="5" Processor="FB_TNJT_023"/>
	</Object>
	<Object Guid="29E1AC6FCCCD482CA6FF1991D6B965EB" Desc="末日教护教骑士" config="FB_TNJT_MS_02" x="210.805038" y="36.347618" z="-331.076843" amount="1" fOrg="0" IsPersistent="0" RefreshTime="-1">
		<Event EventId="5" Processor="FB_TNJT_023"/>
	</Object>
	<Object Guid="B985EDD6783E49E99C9A3F17FC30E891" Desc="猫人复仇者" config="FB_TNJT_NPC_02" x="208.133972" y="36.496326" z="-327.149231" amount="1" fOrg="0" IsPersistent="0" StartIndexNo="1" RefreshTime="-1"/>
	<Object Guid="D9BB8AFA170D4412B6B1DA1DF0997695" Desc="猫人复仇者" config="FB_TNJT_NPC_02" x="210.432175" y="36.409382" z="-330.121033" amount="1" fOrg="0" StartIndexNo="1" IsPersistent="0" RefreshTime="-1"/>
	<Object Guid="653A2C50BAA847ED924301A7FDF75197" Desc="猫人复仇者" config="FB_TNJT_NPC_02" x="203.674774" y="36.996922" z="-329.133392" amount="1" fOrg="0" StartIndexNo="1" IsPersistent="0" RefreshTime="-1"/>
	<Object Guid="20813529D8354BD982FF8D6703A3BF2A" Desc="猫人复仇者" config="FB_TNJT_NPC_02" x="202.54866" y="36.727455" z="-333.649811" amount="1" fOrg="0" StartIndexNo="1" IsPersistent="0" RefreshTime="-1"/>
	<Object Guid="920299950C9B4A29A819810E2BB0038F" Desc="猫人复仇者" config="FB_TNJT_NPC_02" x="212.719727" y="36.599518" z="-322.386139" amount="1" fOrg="0" StartIndexNo="1" IsPersistent="0" RefreshTime="-1"/>
	<Object Guid="661E2F1060CE4742BD992210236C2573" Desc="猫人复仇者" config="FB_TNJT_NPC_02" x="206.79274" y="36.59304" z="-324.032776" amount="1" fOrg="0" StartIndexNo="1" IsPersistent="0" RefreshTime="-1"/>
	<Object Guid="B812D1111EB54489BFA1F8D76489EFA2" Desc="猫人复仇者" config="FB_TNJT_NPC_02" x="218.26181" y="36.391712" z="-332.239471" amount="1" fOrg="0" StartIndexNo="1" IsPersistent="0" RefreshTime="-1"/>
	<Object Guid="505180C4D2924479A2D2F750A8E9AE20" Desc="黑魔法师" config="FB_TNJT_MS_09" x="234.820419" y="37.237064" z="-326.460571" amount="1" fOrg="0" StartIndexNo="1" IsPersistent="0" RefreshTime="-1">
		<Event EventId="5" Processor="FB_TNJT_023"/>
	</Object>
	<Object Guid="291177D9958049A8AC7550203BCDB9DF" Desc="黑魔法师" config="FB_TNJT_MS_09" x="221.671707" y="37.280228" z="-313.869385" amount="1" fOrg="0" IsPersistent="0" RefreshTime="-1">
		<Event EventId="5" Processor="FB_TNJT_023"/>
	</Object>
	<Object Guid="C4DC892C44054F129E6FE40897200FC1" Desc="黑魔法师" config="FB_TNJT_MS_09" x="232.996872" y="36.843021" z="-330.411407" amount="1" fOrg="0" IsPersistent="0" RefreshTime="-1">
		<Event EventId="5" Processor="FB_TNJT_023"/>
	</Object>
	<Object Guid="C280DB50E2034D51A6C84C4AA5433CF0" Desc="末日教士" config="FB_TNJT_MS_06" x="214.92012" y="36.598972" z="-325.754883" amount="1" fOrg="0" StartIndexNo="1" IsPersistent="0" RefreshTime="-1">
		<Event EventId="5" Processor="FB_TNJT_023"/>
	</Object>
	<Object Guid="006E13FADA7840759727568681923F1A" Desc="末日教士" config="FB_TNJT_MS_06" x="218.754807" y="36.800663" z="-320.219055" amount="1" fOrg="0" StartIndexNo="1" IsPersistent="0" RefreshTime="-1">
		<Event EventId="5" Processor="FB_TNJT_023"/>
	</Object>
	<Object Guid="CFFA0497B2BE451FBC72765A158FE30E" Desc="末日学者" config="FB_TNJT_MS_04" x="218.846634" y="36.472782" z="-331.11322" amount="1" fOrg="0" IsPersistent="0" RefreshTime="-1">
		<Event EventId="5" Processor="FB_TNJT_023"/>
	</Object>
	<Object Guid="ADD8556CBF7342C6B21E35AFB116C5B8" Desc="末日学者" config="FB_TNJT_MS_04" x="220.312286" y="36.195354" z="-335.465454" amount="1" fOrg="0" IsPersistent="0" RefreshTime="-1">
		<Event EventId="5" Processor="FB_TNJT_023"/>
	</Object>
	<Object Guid="480E288304F94A8E929C2CCD6218EA60" Desc="末日学者" config="FB_TNJT_MS_04" x="233.652176" y="37.437057" z="-321.812714" amount="1" fOrg="0" IsPersistent="0" RefreshTime="-1">
		<Event EventId="5" Processor="FB_TNJT_023"/>
	</Object>
	<Object Guid="684E9E20037B415DA335D7D6FBB21660" Desc="末日学者" config="FB_TNJT_MS_04" x="229.269241" y="37.567333" z="-315.519226" amount="1" fOrg="0" IsPersistent="0" RefreshTime="-1">
		<Event EventId="5" Processor="FB_TNJT_023"/>
	</Object>
	<Object Guid="F8AA8009A2624CEF92D9F24E0A071613" Desc="FB_TNJT_MS_14" config="FB_TNJT_MS_14" x="222.01709" y="57.205643" z="-196.590149" amount="1" fOrg="0" IsPersistent="0" RefreshTime="-1"/>
	<Object Guid="B4624A4ECEC841A2A48ED0567E6483A4" Desc="末日教官" config="FB_TNJT_BOSS_01" x="251.028107" y="58.180046" z="-257.234375" amount="1" fOrg="0" IsPersistent="0" RefreshTime="-1"/>
	<Object Guid="E3FBA5B5B2194A4985E1FBB70260A28F" Desc="复仇者队长" config="FB_TNJT_NPC_07" x="217.677612" y="36.812004" z="-319.196655" amount="1" fOrg="0" StartIndexNo="1" IsPersistent="0" MaxRefreshCount="" RefreshTime="-1"/>
	<Object Guid="0BD4859B66DD4F0482EF1F463506B321" Desc="猫人复仇者" config="FB_TNJT_NPC_02" x="311.246124" y="76.017006" z="-288.161682" amount="1" fOrg="0" StartIndexNo="2" IsPersistent="0" RefreshTime="-1"/>
	<Object Guid="241060F763144D6692203804430D1F5D" Desc="猫人复仇者" config="FB_TNJT_NPC_02" x="313.791595" y="76.014" z="-296.963135" amount="1" fOrg="0" StartIndexNo="2" IsPersistent="0"/>
	<Object Guid="6E8EE3A251AD4BCEAF9118402570BF3A" Desc="猫人复仇者" config="FB_TNJT_NPC_02" x="313.690948" y="76.014" z="-293.70282" amount="1" fOrg="0" StartIndexNo="2" IsPersistent="0" RefreshTime="-1"/>
	<Object Guid="B763B17CBF404FA8897853EDDC37C80A" Desc="猫人复仇者" config="FB_TNJT_NPC_02" x="309.765717" y="76.020004" z="-292.20575" amount="1" fOrg="0" StartIndexNo="2" IsPersistent="0" RefreshTime="-1"/>
	<Object Guid="FE3C017650404A6AB9B34CE1401E689A" Desc="猫人复仇者" config="FB_TNJT_NPC_02" x="315.939636" y="76.011002" z="-293.440399" amount="1" fOrg="0" StartIndexNo="2" IsPersistent="0"/>
	<Object Guid="01EAFB11FA294B45989A45F6BC8B4C2D" Desc="猫人复仇者" config="FB_TNJT_NPC_02" x="308.862671" y="75.959969" z="-295.172363" amount="1" fOrg="0" StartIndexNo="2" IsPersistent="0" RefreshTime="-1"/>
	<Object Guid="88BA7DDE2D6B4B809FE4D341A4660D79" Desc="猫人复仇者" config="FB_TNJT_NPC_02" x="307.753784" y="76.020004" z="-289.940094" amount="1" fOrg="0" StartIndexNo="2" IsPersistent="0"/>
	<Object Guid="534F9DC09C4A4106B3746010F6CDB494" Desc="猫人复仇者" config="FB_TNJT_NPC_02" x="310.022675" y="76.020004" z="-289.309082" amount="1" fOrg="0" StartIndexNo="2" IsPersistent="0"/>
	<Object Guid="5B31CAB87C674AE68EFB436F270CC1DF" Desc="猫人复仇者" config="FB_TNJT_NPC_02" x="310.467773" y="76.00164" z="-286.94931" amount="1" fOrg="0" StartIndexNo="2" IsPersistent="0"/>
	<Object Guid="3498AEE558A34C0F94C610D2971EF233" Desc="猫人复仇者" config="FB_TNJT_NPC_02" x="315.577942" y="76.011002" z="-286.946625" amount="1" fOrg="0" StartIndexNo="2" IsPersistent="0" RefreshTime="-1"/>
	<Object Guid="3A72FC8E8A6349CCBA3E7E4476EE1297" Desc="猫人复仇者" config="FB_TNJT_NPC_02" x="315.550201" y="76.011002" z="-289.165894" amount="1" fOrg="0" StartIndexNo="2" IsPersistent="0"/>
	<Object Guid="E75E0961B420480B92AD1DDEA45923E1" Desc="猫人复仇者" config="FB_TNJT_NPC_02" x="316.846252" y="76.008003" z="-295.875702" amount="1" fOrg="0" StartIndexNo="2" IsPersistent="0"/>
	<Object Guid="483B71DCCD764F7E82635665CDAF60D2" Desc="猫人复仇者" config="FB_TNJT_NPC_02" x="312.593079" y="76.029007" z="-298.19754" amount="1" fOrg="0" StartIndexNo="2" IsPersistent="0" RefreshTime="-1"/>
	<Object Guid="74A9477B699042BD920ACF90B90E3289" Desc="末日教护教骑士" config="FB_TNJT_MS_02" x="298.389313" y="57.996002" z="-366.803772" amount="1" fOrg="0" IsPersistent="0" RefreshTime="-1"/>
	<Object Guid="64646341AAC24F9280C546E04123E7D3" Desc="末日教护教骑士" config="FB_TNJT_MS_02" x="291.852356" y="58.008003" z="-369.127289" amount="1" fOrg="0" IsPersistent="0" RefreshTime="-1"/>
	<Object Guid="ACD6560976E2479C964ACF724BCFA652" Desc="末日教护教骑士" config="FB_TNJT_MS_02" x="394.448029" y="75.834007" z="-255.614014" amount="1" fOrg="0" IsPersistent="0" RefreshTime="-1"/>
	<Object Guid="42B9E524976D4148BAD4D12280ADB2A0" Desc="末日教护教骑士" config="FB_TNJT_MS_02" x="392.018829" y="75.837006" z="-255.023926" amount="1" fOrg="0" IsPersistent="0" RefreshTime="-1"/>
	<Object Guid="108842E46B574F02A70247342B4219AC" Desc="末日教护教骑士" config="FB_TNJT_MS_02" x="394.750244" y="75.837006" z="-261.283386" amount="1" fOrg="0" IsPersistent="0" RefreshTime="-1"/>
	<Object Guid="8D50A48EF8D741CCBDD16B81E4A5DB83" Desc="监狱栅栏门" config="Organ_tiannu_0003" x="88.38195" y="31.195002" z="-152.855865" amount="1" fOrg="-0.535007" IsPersistent="0" RefreshTime="-1"/>
	<Object Guid="10F5C33BE6C64D9C8E3F0FB3210B3035" Desc="末日教护教骑士" config="FB_TNJT_MS_02" x="395.933563" y="75.834007" z="-259.033905" amount="1" fOrg="0" IsPersistent="0" RefreshTime="-1"/>
	<Object Guid="146B80C3A6CC4724A4AFA33365C793FC" Desc="天怒教堂离开门" config="CloneDoor_tnjt_0002" x="90.149551" y="31.333002" z="-153.389328" amount="1" fOrg="-0.620004" IsPersistent="0" RefreshTime="-1"/>
</Stage>


